tempstorage/TemporaryStorage.py
tempstorage/__init__.py
tempstorage/component.xml
tempstorage/config.py
tempstorage/tests/__init__.py
tempstorage/tests/testTemporaryStorage.py
tempstorage-6.0.dist-info/LICENSE.txt
tempstorage-6.0.dist-info/METADATA
tempstorage-6.0.dist-info/WHEEL
tempstorage-6.0.dist-info/top_level.txt
tempstorage-6.0.dist-info/RECORD
